Metadata-Version: 2.1
Name: HeroesCoC
Version: 0.1.0
Summary: Muestra los niveles actuales de los héroes
Home-page: https://www.clashofstats.com/players/sade-8RC0PLRJQ/army#tabs
Author: Luis Lopez
Classifier: Programming Language :: Python :: 3
Classifier: License :: OSI Approved :: MIT License
Classifier: Operating System :: OS Independent
Requires-Python: >=3.6
